<?xml version="1.0" encoding="UTF-8"?><record_update table="io_set_item">
    <io_set_item action="INSERT_OR_UPDATE">
        <order>10</order>
        <sc_cat_item display_value="Ansible Tower">80de22aadb34a050425f817913961913</sc_cat_item>
        <sys_class_name>io_set_item</sys_class_name>
        <sys_created_by>john.depot</sys_created_by>
        <sys_created_on>2020-12-03 17:28:40</sys_created_on>
        <sys_id>9b91b222db74a050425f81791396198e</sys_id>
        <sys_mod_count>0</sys_mod_count>
        <sys_name>Provision.Ansible Tower</sys_name>
        <sys_package display_value="ACE-ITOM-Showcase" source="x_snc_itom_shocase">8b581e7adb1bdf002c87f1771d9619bf</sys_package>
        <sys_policy/>
        <sys_scope display_value="ACE-ITOM-Showcase">8b581e7adb1bdf002c87f1771d9619bf</sys_scope>
        <sys_update_name>io_set_item_9b91b222db74a050425f81791396198e</sys_update_name>
        <sys_updated_by>john.depot</sys_updated_by>
        <sys_updated_on>2020-12-03 17:28:40</sys_updated_on>
        <variable_set display_value="Provision">1391b222db74a050425f81791396198e</variable_set>
    </io_set_item>
</record_update>
