<?xml version="1.0" encoding="UTF-8"?><record_update sys_domain="global" table="sn_cmp_cloud_template">
    <sn_cmp_cloud_template action="INSERT_OR_UPDATE">
        <body>AWSTemplateFormatVersion: 2010-09-09
Description: &gt;-
  AWS CloudFormation Template ACE-MSP-Monitoring-VMs-v1: A Template for
  provisioning the Monitoring VMs for the MSP Stack used in the ACE ITOM End To
  End Demo. **WARNING** This template creates 3 Amazon EC2 instances. You will
  be billed for the AWS resources used if you create a stack from this template.
Metadata:
  'AWS::CloudFormation::Designer':
    96ddedfe-6e9f-425f-bf4b-9849f8b29032:
      size:
        width: 60
        height: 60
      position:
        x: -10
        'y': 90
      z: 1
      embeds: []
    3deeb2f4-8c1d-4426-8e92-de4fbb8352a2:
      size:
        width: 60
        height: 60
      position:
        x: 150
        'y': 90
      z: 1
      embeds: []
    65d46d62-da3a-4151-9dca-a387b4eb1768:
      size:
        width: 60
        height: 60
      position:
        x: 70
        'y': 90
      z: 1
      embeds: []
    b094e0ea-e4d7-40fe-b9c5-5b33c562c1cd:
      size:
        width: 60
        height: 60
      position:
        x: -130
        'y': 90
      z: 0
      embeds: []
    64526e66-f1c9-4d7e-9b45-8c0fbee8645d:
      source:
        id: b094e0ea-e4d7-40fe-b9c5-5b33c562c1cd
      target:
        id: 96ddedfe-6e9f-425f-bf4b-9849f8b29032
      z: 0
Resources:
  LoadBalancer:
    Type: 'AWS::EC2::Instance'
    Properties:
      InstanceType: t2.small
      ImageId: !Ref LBAMI
      SubnetId: !Ref SubNet
      SecurityGroupIds:
        - !Ref SecGroup
      KeyName: ACE-Linux-SSH
      Tags:
        - Key: Name
          Value: !Join 
            - ''
            - - ACE-MSP-LB-
              - !Ref LABCODE
        - Key: OSType
          Value: Linux
    Metadata:
      'AWS::CloudFormation::Designer':
        id: 96ddedfe-6e9f-425f-bf4b-9849f8b29032
  Nagios:
    Type: 'AWS::EC2::Instance'
    Metadata:
      'AWS::CloudFormation::Designer':
        id: 65d46d62-da3a-4151-9dca-a387b4eb1768
    Properties:
      InstanceType: t2.small
      ImageId: !Ref NAGIOSAMI
      SubnetId: !Ref SubNet
      SecurityGroupIds:
        - !Ref SecGroup
      KeyName: ACE-Linux-SSH
      Tags:
        - Key: Name
          Value: !Join 
            - ''
            - - ACE-MSP-Nagios-
              - !Ref LABCODE
        - Key: OSType
          Value: Linux
  Zabbix:
    Type: 'AWS::EC2::Instance'
    Properties:
      InstanceType: t2.small
      ImageId: !Ref ZABBIXAMI
      SubnetId: !Ref SubNet
      SecurityGroupIds:
        - !Ref SecGroup
      KeyName: ACE-Linux-SSH
      Tags:
        - Key: Name
          Value: !Join 
            - ''
            - - ACE-MSP-Zabbix-
              - !Ref LABCODE
        - Key: OSType
          Value: Linux
    Metadata:
      'AWS::CloudFormation::Designer':
        id: 3deeb2f4-8c1d-4426-8e92-de4fbb8352a2
  EC2EIPATJ0B:
    Type: 'AWS::EC2::EIPAssociation'
    Properties:
      AllocationId: !GetAtt 
        - ElasticIP
        - AllocationId
      InstanceId: !Ref LoadBalancer
    Metadata:
      'AWS::CloudFormation::Designer':
        id: 64526e66-f1c9-4d7e-9b45-8c0fbee8645d
  ElasticIP:
    Type: 'AWS::EC2::EIP'
    Properties:
      Domain: vpc
    Metadata:
      'AWS::CloudFormation::Designer':
        id: b094e0ea-e4d7-40fe-b9c5-5b33c562c1cd
Parameters:
  LABCODE:
    Description: Users LAB Code
    Type: String
  SubNet:
    Description: VPC Subnet
    Type: String
    Default: subnet-0fafceb72d2a5c41e
  SecGroup:
    Description: Security Group
    Type: String
    Default: sg-0d93dcf2e42ac18a8
  LBAMI:
    Description: Load Balancer AMI
    Type: String
    Default: ami-03ac3fe926266d6f5
  NAGIOSAMI:
    Description: Nagios AMI
    Type: String
    Default: ami-0fb0b3991072a2cab
  ZABBIXAMI:
    Description: Zabbix AMI
    Type: String
    Default: ami-027c9e4293f869f2f
</body>
        <format display_value="YAML">0fd3bffc872313008de7483cf6cb0b48</format>
        <name>AWS Deploy Monitoring Servers</name>
        <published>true</published>
        <resource_block display_value="AWS Deploy Monitoring Servers">80045442db6048d0a9ed3967f4961960</resource_block>
        <short_description>ACE-MSP-Monitoring-VMs-v2</short_description>
        <sys_class_name>sn_cmp_cloud_template</sys_class_name>
        <sys_created_by>david.loo</sys_created_by>
        <sys_created_on>2019-10-18 13:45:51</sys_created_on>
        <sys_domain>global</sys_domain>
        <sys_id>e29f8c4adb2048d0a9ed3967f4961976</sys_id>
        <sys_mod_count>2</sys_mod_count>
        <sys_name>AWS Deploy Monitoring Servers</sys_name>
        <sys_package display_value="ACE-ITOM-Showcase" source="x_snc_itom_shocase">8b581e7adb1bdf002c87f1771d9619bf</sys_package>
        <sys_policy/>
        <sys_scope display_value="ACE-ITOM-Showcase">8b581e7adb1bdf002c87f1771d9619bf</sys_scope>
        <sys_update_name>sn_cmp_cloud_template_e29f8c4adb2048d0a9ed3967f4961976</sys_update_name>
        <sys_updated_by>david.loo</sys_updated_by>
        <sys_updated_on>2019-10-18 14:05:15</sys_updated_on>
        <template_url/>
        <type display_value="CloudFormation Template">932f81e49f00320048111f80a57fcf6e</type>
        <use_template_body>true</use_template_body>
    </sn_cmp_cloud_template>
</record_update>
