<?xml version="1.0" encoding="UTF-8"?><record_update table="sn_cmp_rb_op_impl_param">
    <sn_cmp_rb_op_impl_param action="INSERT_OR_UPDATE">
        <applicable_to/>
        <datasource>1</datasource>
        <datasourcevalue/>
        <defaultvalue>${parameter.CustomTags}</defaultvalue>
        <error_text/>
        <help_text/>
        <host/>
        <ismandatory>false</ismandatory>
        <name>CustomTags</name>
        <op_param display_value="CustomTags">15049442db6048d0a9ed3967f4961975</op_param>
        <operation display_value="Provision">c1049442db6048d0a9ed3967f496192e</operation>
        <order>60</order>
        <read_only>false</read_only>
        <regex/>
        <step display_value="Stack Orchestration Interface.Create Stack">41049442db6048d0a9ed3967f4961949</step>
        <sys_class_name>sn_cmp_rb_op_impl_param</sys_class_name>
        <sys_created_by>david.loo</sys_created_by>
        <sys_created_on>2019-10-18 14:05:10</sys_created_on>
        <sys_id>95049442db6048d0a9ed3967f4961974</sys_id>
        <sys_mod_count>1</sys_mod_count>
        <sys_name>CustomTags</sys_name>
        <sys_package display_value="ACE-ITOM-Showcase" source="x_snc_itom_shocase">8b581e7adb1bdf002c87f1771d9619bf</sys_package>
        <sys_policy/>
        <sys_scope display_value="ACE-ITOM-Showcase">8b581e7adb1bdf002c87f1771d9619bf</sys_scope>
        <sys_update_name>sn_cmp_rb_op_impl_param_95049442db6048d0a9ed3967f4961974</sys_update_name>
        <sys_updated_by>david.loo</sys_updated_by>
        <sys_updated_on>2019-10-18 14:05:10</sys_updated_on>
        <ui_data_type/>
        <value/>
        <visibilty>false</visibilty>
    </sn_cmp_rb_op_impl_param>
</record_update>
